[{"text": "Table", "children": [{"text": "Regular table", "children": [{"text": "Tabletop", "children": [{"text": "Tabletop surface", "children": [{"text": "Glass", "objs": ["original-1"], "id": 51, "name": "glass"}], "id": 45, "name": "tabletop_surface"}, {"text": "Tabletop frame", "children": [{"text": "Bar", "objs": ["new-6"], "id": 47, "name": "bar"}, {"text": "Bar", "objs": ["new-4"], "id": 48, "name": "bar"}, {"text": "Bar", "objs": ["new-5"], "id": 49, "name": "bar"}, {"text": "Bar", "objs": ["new-7"], "id": 50, "name": "bar"}], "id": 46, "name": "tabletop_frame"}], "id": 2, "name": "tabletop"}, {"text": "Table Base", "children": [{"text": "Shelving Base", "children": [{"text": "Tabletop Connector", "objs": ["original-6"], "id": 10, "name": "tabletop_connector"}, {"text": "Tabletop Connector", "objs": ["original-4"], "id": 11, "name": "tabletop_connector"}, {"text": "Tabletop Connector", "objs": ["original-5"], "id": 12, "name": "tabletop_connector"}, {"text": "Tabletop Connector", "objs": ["original-9"], "id": 13, "name": "tabletop_connector"}, {"text": "Shelf", "objs": ["original-3"], "id": 14, "name": "shelf"}, {"text": "Wheel Assembly", "children": [{"text": "Caster Stem", "objs": ["original-16"], "id": 69, "name": "caster_stem"}, {"text": "Wheel", "objs": ["original-18"], "id": 70, "name": "wheel"}, {"text": "Wheel", "objs": ["original-19"], "id": 71, "name": "wheel"}, {"text": "Brake", "objs": ["original-17"], "id": 72, "name": "brake"}], "id": 15, "name": "caster"}, {"text": "Wheel Assembly", "children": [{"text": "Caster Stem", "objs": ["original-21"], "id": 65, "name": "caster_stem"}, {"text": "Wheel", "objs": ["original-24"], "id": 66, "name": "wheel"}, {"text": "Wheel", "objs": ["original-23"], "id": 67, "name": "wheel"}, {"text": "Brake", "objs": ["original-22"], "id": 68, "name": "brake"}], "id": 16, "name": "caster"}, {"text": "Wheel Assembly", "children": [{"text": "Caster Stem", "objs": ["original-26"], "id": 61, "name": "caster_stem"}, {"text": "Wheel", "objs": ["original-29"], "id": 62, "name": "wheel"}, {"text": "Wheel", "objs": ["original-28"], "id": 63, "name": "wheel"}, {"text": "Brake", "objs": ["original-27"], "id": 64, "name": "brake"}], "id": 17, "name": "caster"}, {"text": "Wheel Assembly", "children": [{"text": "Caster Stem", "objs": ["original-11"], "id": 57, "name": "caster_stem"}, {"text": "Wheel", "objs": ["original-13"], "id": 58, "name": "wheel"}, {"text": "Wheel", "objs": ["original-14"], "id": 59, "name": "wheel"}, {"text": "Brake", "objs": ["original-12"], "id": 60, "name": "brake"}], "id": 18, "name": "caster"}, {"text": "Tabletop Connector", "objs": ["original-8"], "id": 19, "name": "tabletop_connector"}, {"text": "Tabletop Connector", "objs": ["original-7"], "id": 20, "name": "tabletop_connector"}, {"text": "Leg", "objs": ["new-2"], "id": 41, "name": "leg"}, {"text": "Leg", "objs": ["new-1"], "id": 42, "name": "leg"}, {"text": "Leg", "objs": ["new-0"], "id": 43, "name": "leg"}, {"text": "Leg", "objs": ["new-3"], "id": 44, "name": "leg"}], "id": 4, "name": "shelving_base"}], "id": 3, "name": "table_base"}], "id": 1, "name": "regular_table"}], "id": 0, "name": "table"}]