[{"text": "Dish Washer", "children": [{"text": "Body", "children": [{"text": "Body Interior", "children": [{"text": "Shelf", "objs": ["original-3"], "id": 16, "name": "shelf"}, {"text": "Shelf", "objs": ["original-4"], "id": 17, "name": "shelf"}, {"text": "bowl (other)", "children": [{"text": "other_leaf", "objs": ["original-12", "original-9", "original-7", "original-5", "original-14", "original-11", "original-10", "original-8", "original-6", "original-13"], "id": 19, "name": "other_leaf"}], "id": 18, "name": "other"}], "id": 6, "name": "body_interior"}, {"text": "Door", "children": [{"text": "Handle", "objs": ["new-2"], "id": 12, "name": "handle"}, {"text": "Glass", "objs": ["new-4"], "id": 13, "name": "glass"}, {"text": "Door Frame", "objs": ["new-5"], "id": 20, "name": "door_frame"}], "id": 7, "name": "door"}, {"text": "Side Controls", "children": [{"text": "Display Panel", "objs": ["new-3"], "id": 11, "name": "display_panel"}], "id": 8, "name": "side_controls"}, {"text": "Frame", "objs": ["new-1", "new-0", "original-18"], "id": 15, "name": "frame"}], "id": 1, "name": "body"}], "id": 0, "name": "dishwasher"}]